mcp_f1data/__init__.py
mcp_f1data/__main__.py
mcp_f1data/server/__init__.py
mcp_f1data/server/mcp_server.py
mcp_f1data/tools/__init__.py
mcp_f1data/tools/fastf1_tools.py
mcp_f1data/utils/__init__.py
mcp_f1data/utils/fastf1_utils.py
mcp_f1data-0.1.5.dist-info/licenses/LICENSE
mcp_f1data-0.1.5.dist-info/METADATA
mcp_f1data-0.1.5.dist-info/WHEEL
mcp_f1data-0.1.5.dist-info/entry_points.txt
mcp_f1data-0.1.5.dist-info/top_level.txt
mcp_f1data-0.1.5.dist-info/RECORD
