Metadata-Version: 2.4
Name: mcp_f1data
Version: 0.1.5
Summary: MCP server for F1 data using Fastf1, OpenF1 or Ergast APIs
Project-URL: Homepage, https://github.com/maxbleu/mcp_f1data
Project-URL: Repository, https://github.com/maxbleu/mcp_f1data
Project-URL: Issues, https://github.com/maxbleu/mcp_f1data/issues
Classifier: Programming Language :: Python :: 3
Classifier: Programming Language :: Python :: 3.12
Classifier: License :: OSI Approved :: MIT License
Classifier: Operating System :: OS Independent
Requires-Python: >=3.12
License-File: LICENSE
Requires-Dist: fastf1<4.0.0,>=3.4.5
Requires-Dist: pandas<2.2.0,>=1.1.0
Requires-Dist: fastmcp<3.0.0,>=2.5.1
Requires-Dist: websockets>=14.0
Requires-Dist: mcp<2.0.0,>=1.9.4
Requires-Dist: pydantic<3.0.0,>=2.11.1
Dynamic: license-file
